codegraph_mcp/__init__.py
codegraph_mcp/__main__.py
codegraph_mcp/config.py
codegraph_mcp/server.py
codegraph_mcp/core/__init__.py
codegraph_mcp/core/community.py
codegraph_mcp/core/engine_manager.py
codegraph_mcp/core/graph.py
codegraph_mcp/core/graphrag.py
codegraph_mcp/core/indexer.py
codegraph_mcp/core/llm.py
codegraph_mcp/core/parser.py
codegraph_mcp/core/semantic.py
codegraph_mcp/languages/__init__.py
codegraph_mcp/languages/config.py
codegraph_mcp/languages/cpp.py
codegraph_mcp/languages/csharp.py
codegraph_mcp/languages/go.py
codegraph_mcp/languages/hcl.py
codegraph_mcp/languages/java.py
codegraph_mcp/languages/javascript.py
codegraph_mcp/languages/php.py
codegraph_mcp/languages/python.py
codegraph_mcp/languages/ruby.py
codegraph_mcp/languages/rust.py
codegraph_mcp/languages/typescript.py
codegraph_mcp/mcp/__init__.py
codegraph_mcp/mcp/prompts.py
codegraph_mcp/mcp/resources.py
codegraph_mcp/mcp/tools.py
codegraph_mcp/storage/__init__.py
codegraph_mcp/storage/cache.py
codegraph_mcp/storage/sqlite.py
codegraph_mcp/storage/vectors.py
codegraph_mcp/utils/__init__.py
codegraph_mcp/utils/git.py
codegraph_mcp/utils/logging.py
codegraph_mcp_server-0.7.3.dist-info/METADATA
codegraph_mcp_server-0.7.3.dist-info/WHEEL
codegraph_mcp_server-0.7.3.dist-info/entry_points.txt
codegraph_mcp_server-0.7.3.dist-info/licenses/LICENSE
codegraph_mcp_server-0.7.3.dist-info/RECORD
