Metadata-Version: 2.4
Name: codegraph-mcp-server
Version: 0.7.3
Summary: MCP Server for code graph analysis with GraphRAG capabilities
Project-URL: Homepage, https://github.com/nahisaho/CodeGraphMCPServer
Project-URL: Documentation, https://github.com/nahisaho/CodeGraphMCPServer#readme
Project-URL: Repository, https://github.com/nahisaho/CodeGraphMCPServer.git
Project-URL: Issues, https://github.com/nahisaho/CodeGraphMCPServer/issues
Author: nahisaho
License: MIT
License-File: LICENSE
Keywords: ast,code-analysis,graphrag,mcp,tree-sitter
Classifier: Development Status :: 3 - Alpha
Classifier: Intended Audience :: Developers
Classifier: License :: OSI Approved :: MIT License
Classifier: Programming Language :: Python :: 3.11
Classifier: Programming Language :: Python :: 3.12
Classifier: Topic :: Software Development :: Code Generators
Classifier: Topic :: Software Development :: Compilers
Requires-Python: >=3.11
Requires-Dist: aiosqlite>=0.19.0
Requires-Dist: gitpython>=3.1.0
Requires-Dist: mcp>=1.0.0
Requires-Dist: networkx>=3.0
Requires-Dist: numpy>=1.24.0
Requires-Dist: pydantic-settings>=2.0.0
Requires-Dist: pydantic>=2.0.0
Requires-Dist: rich>=13.0.0
Requires-Dist: tiktoken>=0.5.0
Requires-Dist: tree-sitter-c-sharp>=0.21.0
Requires-Dist: tree-sitter-cpp>=0.21.0
Requires-Dist: tree-sitter-go>=0.21.0
Requires-Dist: tree-sitter-hcl>=0.21.0
Requires-Dist: tree-sitter-java>=0.21.0
Requires-Dist: tree-sitter-javascript>=0.21.0
Requires-Dist: tree-sitter-php>=0.21.0
Requires-Dist: tree-sitter-python>=0.21.0
Requires-Dist: tree-sitter-ruby>=0.21.0
Requires-Dist: tree-sitter-rust>=0.21.0
Requires-Dist: tree-sitter-typescript>=0.21.0
Requires-Dist: tree-sitter>=0.21.0
Requires-Dist: typer>=0.9.0
Requires-Dist: watchfiles>=0.21.0
Provides-Extra: all
Requires-Dist: codegraph-mcp[dev,docs,embeddings,openai,sse]; extra == 'all'
Provides-Extra: dev
Requires-Dist: mypy>=1.0.0; extra == 'dev'
Requires-Dist: pre-commit>=3.0.0; extra == 'dev'
Requires-Dist: pytest-asyncio>=0.21.0; extra == 'dev'
Requires-Dist: pytest-cov>=4.0.0; extra == 'dev'
Requires-Dist: pytest>=7.0.0; extra == 'dev'
Requires-Dist: ruff>=0.1.0; extra == 'dev'
Provides-Extra: docs
Requires-Dist: mkdocs-material>=9.0.0; extra == 'docs'
Requires-Dist: mkdocs>=1.5.0; extra == 'docs'
Requires-Dist: mkdocstrings[python]>=0.24.0; extra == 'docs'
Provides-Extra: embeddings
Requires-Dist: sentence-transformers>=2.2.0; extra == 'embeddings'
Provides-Extra: openai
Requires-Dist: openai>=1.0.0; extra == 'openai'
Provides-Extra: sse
Requires-Dist: starlette>=0.27.0; extra == 'sse'
Requires-Dist: uvicorn>=0.23.0; extra == 'sse'
